CONTRIBUTORS.rst
LICENSE.txt
MANIFEST.in
README.rst
ikp3db.py
iksettrace3.c
setup.py
ikp3db.egg-info/PKG-INFO
ikp3db.egg-info/SOURCES.txt
ikp3db.egg-info/dependency_links.txt
ikp3db.egg-info/top_level.txt