Metadata-Version: 1.1
Name: ikp3db
Version: 1.0
Summary: A hackable CPython 3.6+ remote debugger designed for the Web and online IDE integration. Fork of IKPdb.
Home-page: https://github.com/cmorisse/ikp3db
Author: Cyril MORISSE, Audaxis
Author-email: cmorisse@boxes3.net
License: MIT
Keywords: debugger debug remote tcp
Platform: UNKNOWN
Classifier: Development Status :: 4 - Beta
Classifier: Environment :: Web Environment
Classifier: Intended Audience :: Developers
Classifier: Topic :: Software Development :: Debuggers
Classifier: License :: OSI Approved :: MIT License
Classifier: Programming Language :: Python
Classifier: Natural Language :: English
